verlanize/__init__.py
verlanize-2.0.1.dist-info/DESCRIPTION.rst
verlanize-2.0.1.dist-info/METADATA
verlanize-2.0.1.dist-info/RECORD
verlanize-2.0.1.dist-info/WHEEL
verlanize-2.0.1.dist-info/metadata.json
verlanize-2.0.1.dist-info/top_level.txt
