Metadata-Version: 2.0
Name: verlanize
Version: 2.0.1
Summary: Translate french text to verlan
Home-page: https://github.com/vigneras/verlanize
Author: Pierre Vigneras
Author-email: pierre.vigneras@gmail.com
License: UNKNOWN
Project-URL: Funding, https://paypal.me/pierrevigneras
Project-URL: Bug Reports, https://github.com/vigneras/verlanize/issues
Project-URL: Source, https://github.com/vigneras/verlanize
Project-URL: Say Thanks!, https://saythanks.io/to/vigneras
Keywords: text french verlan
Platform: UNKNOWN
Classifier: Development Status :: 3 - Alpha
Classifier: Intended Audience :: Developers
Classifier: Topic :: Text Processing :: Linguistic
Classifier: Natural Language :: French
Classifier: License :: OSI Approved :: GNU General Public License v3 (GPLv3)
Classifier: Programming Language :: Python :: 2
Classifier: Programming Language :: Python :: 2.7
Classifier: Programming Language :: Python :: 3
Classifier: Programming Language :: Python :: 3.4
Classifier: Programming Language :: Python :: 3.5
Classifier: Programming Language :: Python :: 3.6
Provides-Extra: dev
Provides-Extra: test
Provides-Extra: dev
Requires-Dist: check-manifest; extra == 'dev'
Provides-Extra: test
Requires-Dist: coverage; extra == 'test'
